taras
