Metadata-Version: 1.0
Name: taras.recipe.distutils
Version: 0.1.3final
Summary: Recipe for zc.buildout that downloads one or multiple distutils-archives and installs them without requiring for zc.distutils to be installed.
Home-page: http://github.com/taras/taras.recipe.distutils
Author: Taras Mankovski
Author-email: tarasm@gmail.com
License: BSD License
Keywords: distutils buildout
Platform: UNKNOWN
Classifier: Development Status :: 3 - Alpha
Classifier: Environment :: Plugins
Classifier: Framework :: Buildout
Classifier: Intended Audience :: Developers
Classifier: Programming Language :: Python
Classifier: Topic :: Software Development :: Libraries :: Python Modules
Classifier: Topic :: System :: Installation/Setup
Classifier: License :: OSI Approved :: BSD License
